decorpack/__init__.py
decorpack/logger.py
decorpack/singleton.py
decorpack/timer.py
decorpack/try_except.py
decorpack/wrapper_utils.py
decorpack-0.1.2.dist-info/METADATA
decorpack-0.1.2.dist-info/WHEEL
decorpack-0.1.2.dist-info/licenses/LICENSE
decorpack-0.1.2.dist-info/RECORD
