Metadata-Version: 2.4
Name: decorpack
Version: 0.1.2
Summary: Add your description here
Author: Pierre LAPOLLA
License: MIT License
License-File: LICENSE
Requires-Python: >=3.13
Requires-Dist: dotenv>=0.9.9
Requires-Dist: structlog>=25.3.0
